LICENSE
README.md
setup.py
CVE_2024_24919.egg-info/PKG-INFO
CVE_2024_24919.egg-info/SOURCES.txt
CVE_2024_24919.egg-info/dependency_links.txt
CVE_2024_24919.egg-info/entry_points.txt
CVE_2024_24919.egg-info/requires.txt
CVE_2024_24919.egg-info/top_level.txt
cve202424919/__init__.py
cve202424919/main.py
cve202424919/includes/__init__.py
cve202424919/includes/bot.py
cve202424919/includes/filereader.py
cve202424919/includes/scan.py
cve202424919/includes/writefile.py
cve202424919/utils/__init__.py
cve202424919/utils/configure.py
cve202424919/utils/const.py
cve202424919/utils/helpers.py
cve202424919/utils/status.py